sysnet_pyutils/__init__.py
sysnet_pyutils/barcode.py
sysnet_pyutils/constants.py
sysnet_pyutils/data_utils.py
sysnet_pyutils/domino.py
sysnet_pyutils/geo.py
sysnet_pyutils/ident.py
sysnet_pyutils/log.py
sysnet_pyutils/ses.py
sysnet_pyutils/tools.py
sysnet_pyutils/utils.py
sysnet_pyutils/cron_utils/__init__.py
sysnet_pyutils/cron_utils/validation.py
sysnet_pyutils/models/__init__.py
sysnet_pyutils/models/general.py
sysnet_pyutils/syslog/__init__.py
sysnet_pyutils/syslog/factory.py
sysnet_pyutils-1.6.1.dist-info/licenses/LICENSE
sysnet_pyutils-1.6.1.dist-info/METADATA
sysnet_pyutils-1.6.1.dist-info/WHEEL
sysnet_pyutils-1.6.1.dist-info/top_level.txt
sysnet_pyutils-1.6.1.dist-info/RECORD
