Metadata-Version: 2.4
Name: sysnet-pyutils
Version: 1.6.1
Summary: Python Utilities
Author-email: Data Developer <info@sysnet.cz>
Project-URL: Homepage, https://github.com/SYSNET-CZ/pyutils
Classifier: Development Status :: 5 - Production/Stable
Classifier: Programming Language :: Python :: 3
Classifier: Intended Audience :: Developers
Classifier: License :: Free For Home Use
Classifier: Natural Language :: Czech
Classifier: Operating System :: OS Independent
Classifier: Topic :: Software Development :: Libraries
Requires-Python: >=3.10
License-File: LICENSE
Requires-Dist: typing-extensions>=4.12.0
Requires-Dist: PyYAML>=6.0.1
Requires-Dist: pytz>=2023.3
Requires-Dist: python-dateutil>=2.8.2
Requires-Dist: xmltodict>=1.0.0
Requires-Dist: boto3>=1.34.34
Requires-Dist: botocore>=1.34.34
Requires-Dist: pymongo>=4.7.2
Requires-Dist: pydantic[email]>=2.10.6
Requires-Dist: croniter>=6.0.0
Dynamic: license-file
